pandas_utils/__init__.py
pandas_utils/utils.py
pandas_utils-0.1.4.dist-info/WHEEL
pandas_utils-0.1.4.dist-info/METADATA
pandas_utils-0.1.4.dist-info/RECORD
