Metadata-Version: 2.1
Name: pandas-utils
Version: 0.1.4
Summary: 
Author: rschmidtner
Author-email: RSchmidtner@NewYorker.de
Requires-Python: >=3.6.1,<4.0.0
Classifier: Programming Language :: Python :: 3
Classifier: Programming Language :: Python :: 3.7
Classifier: Programming Language :: Python :: 3.8
Classifier: Programming Language :: Python :: 3.9
Requires-Dist: pandas (>=1.1.5,<2.0.0)
